[
  {
    "all_phones_from_home_page": null,
    "byear": null,
    "email3": null,
    "homephone": null,
    "firstname": "",
    "all_email_from_home_page": null,
    "id": null,
    "bmonth": null,
    "mobilephone": null,
    "company": "",
    "email2": null,
    "workphone": null,
    "bday": null,
    "nickname": "",
    "lastname": "",
    "py/object": "model.contact.Contact",
    "address": "",
    "email": "",
    "secondaryphone": null,
    "middlename": ""
  },
  {
    "all_phones_from_home_page": null,
    "byear": null,
    "email3": null,
    "homephone": "3434343",
    "firstname": "\u0423\u043b\u044c\u044f\u043d\u0430",
    "all_email_from_home_page": null,
    "id": null,
    "bmonth": null,
    "mobilephone": "4454545",
    "company": "1c",
    "email2": null,
    "workphone": "657676",
    "bday": null,
    "nickname": "ulik",
    "lastname": "\u0412\u0430\u0442\u0440\u0430\u043a\u0448\u0438\u043d\u0430",
    "py/object": "model.contact.Contact",
    "address": "\u0434\u043c\u0438\u0442\u0440\u043e\u0432\u0441\u043a\u043e\u0435 \u0448 9",
    "email": "ulikwwwww@ya.ru",
    "secondaryphone": "88888",
    "middlename": "\u0412\u043b\u0430\u0434\u0438\u043c\u0438\u0440\u043e\u0432\u043d\u0430"
  },
  {
    "all_phones_from_home_page": null,
    "byear": null,
    "email3": null,
    "homephone": null,
    "firstname": "firstname@Q,Et0zuJya?* |>N M, g",
    "all_email_from_home_page": null,
    "id": null,
    "bmonth": null,
    "mobilephone": null,
    "company": null,
    "email2": null,
    "workphone": null,
    "bday": null,
    "nickname": null,
    "lastname": "lastnameFF_,`",
    "py/object": "model.contact.Contact",
    "address": null,
    "email": null,
    "secondaryphone": null,
    "middlename": "middlenameg96e+>tlt9z"
  }
]